[
    {
        "Rank": 1,
        "Name": "Ja'Marr Chase",
        "Team": "CIN",
        "Position": "WR",
        "Position Rank": 1,
        "ADP": 1.0
    },
    {
        "Rank": 2,
        "Name": "Bijan Robinson",
        "Team": "ATL",
        "Position": "RB",
        "Position Rank": 1,
        "ADP": 2.5
    },
    {
        "Rank": 3,
        "Name": "CeeDee Lamb",
        "Team": "DAL",
        "Position": "WR",
        "Position Rank": 2,
        "ADP": 5.2
    },
    {
        "Rank": 4,
        "Name": "Justin Jefferson",
        "Team": "MIN",
        "Position": "WR",
        "Position Rank": 3,
        "ADP": 4.8
    },
    {
        "Rank": 5,
        "Name": "Jahmyr Gibbs",
        "Team": "DET",
        "Position": "RB",
        "Position Rank": 2,
        "ADP": 4.3
    },
    {
        "Rank": 6,
        "Name": "Saquon Barkley",
        "Team": "PHI",
        "Position": "RB",
        "Position Rank": 3,
        "ADP": 3.3
    },
    {
        "Rank": 7,
        "Name": "Malik Nabers",
        "Team": "NYG",
        "Position": "WR",
        "Position Rank": 4,
        "ADP": 9.8
    },
    {
        "Rank": 8,
        "Name": "Amon-Ra St. Brown",
        "Team": "DET",
        "Position": "WR",
        "Position Rank": 5,
        "ADP": 9.3
    },
    {
        "Rank": 9,
        "Name": "Nico Collins",
        "Team": "HOU",
        "Position": "WR",
        "Position Rank": 6,
        "ADP": 13.5
    },
    {
        "Rank": 10,
        "Name": "Puka Nacua",
        "Team": "LAR",
        "Position": "WR",
        "Position Rank": 7,
        "ADP": 10.2
    },
    {
        "Rank": 11,
        "Name": "Christian McCaffrey",
        "Team": "SF",
        "Position": "RB",
        "Position Rank": 4,
        "ADP": 8.5
    },
    {
        "Rank": 12,
        "Name": "Brian Thomas Jr.",
        "Team": "JAC",
        "Position": "WR",
        "Position Rank": 8,
        "ADP": 15.2
    },
    {
        "Rank": 13,
        "Name": "Drake London",
        "Team": "ATL",
        "Position": "WR",
        "Position Rank": 9,
        "ADP": 19.7
    },
    {
        "Rank": 14,
        "Name": "Ashton Jeanty",
        "Team": "LV",
        "Position": "RB",
        "Position Rank": 5,
        "ADP": 10.3
    },
    {
        "Rank": 15,
        "Name": "A.J. Brown",
        "Team": "PHI",
        "Position": "WR",
        "Position Rank": 10,
        "ADP": 20.0
    },
    {
        "Rank": 16,
        "Name": "De'Von Achane",
        "Team": "MIA",
        "Position": "RB",
        "Position Rank": 6,
        "ADP": 14.3
    },
    {
        "Rank": 17,
        "Name": "Brock Bowers",
        "Team": "LV",
        "Position": "TE",
        "Position Rank": 1,
        "ADP": 19.3
    },
    {
        "Rank": 18,
        "Name": "Ladd McConkey",
        "Team": "LAC",
        "Position": "WR",
        "Position Rank": 11,
        "ADP": 26.0
    },
    {
        "Rank": 19,
        "Name": "Trey McBride",
        "Team": "ARI",
        "Position": "TE",
        "Position Rank": 2,
        "ADP": 27.5
    },
    {
        "Rank": 20,
        "Name": "Derrick Henry",
        "Team": "BAL",
        "Position": "RB",
        "Position Rank": 7,
        "ADP": 10.0
    },
    {
        "Rank": 21,
        "Name": "Jaxon Smith-Njigba",
        "Team": "SEA",
        "Position": "WR",
        "Position Rank": 12,
        "ADP": 34.0
    },
    {
        "Rank": 22,
        "Name": "Tee Higgins",
        "Team": "CIN",
        "Position": "WR",
        "Position Rank": 13,
        "ADP": 30.3
    },
    {
        "Rank": 23,
        "Name": "Chase Brown",
        "Team": "CIN",
        "Position": "RB",
        "Position Rank": 8,
        "ADP": 24.7
    },
    {
        "Rank": 24,
        "Name": "Josh Allen",
        "Team": "BUF",
        "Position": "QB",
        "Position Rank": 1,
        "ADP": 20.8
    },
    {
        "Rank": 25,
        "Name": "Bucky Irving",
        "Team": "TB",
        "Position": "RB",
        "Position Rank": 9,
        "ADP": 21.8
    },
    {
        "Rank": 26,
        "Name": "Lamar Jackson",
        "Team": "BAL",
        "Position": "QB",
        "Position Rank": 2,
        "ADP": 21.3
    },
    {
        "Rank": 27,
        "Name": "Garrett Wilson",
        "Team": "NYJ",
        "Position": "WR",
        "Position Rank": 14,
        "ADP": 39.7
    },
    {
        "Rank": 28,
        "Name": "Josh Jacobs",
        "Team": "GB",
        "Position": "RB",
        "Position Rank": 10,
        "ADP": 16.3
    },
    {
        "Rank": 29,
        "Name": "Jonathan Taylor",
        "Team": "IND",
        "Position": "RB",
        "Position Rank": 11,
        "ADP": 19.8
    },
    {
        "Rank": 30,
        "Name": "Tyreek Hill",
        "Team": "MIA",
        "Position": "WR",
        "Position Rank": 15,
        "ADP": 32.2
    },
    {
        "Rank": 31,
        "Name": "George Kittle",
        "Team": "SF",
        "Position": "TE",
        "Position Rank": 3,
        "ADP": 37.8
    },
    {
        "Rank": 32,
        "Name": "Davante Adams",
        "Team": "LAR",
        "Position": "WR",
        "Position Rank": 16,
        "ADP": 39.3
    },
    {
        "Rank": 33,
        "Name": "Mike Evans",
        "Team": "TB",
        "Position": "WR",
        "Position Rank": 17,
        "ADP": 38.8
    },
    {
        "Rank": 34,
        "Name": "Jayden Daniels",
        "Team": "WAS",
        "Position": "QB",
        "Position Rank": 3,
        "ADP": 30.8
    },
    {
        "Rank": 35,
        "Name": "Kyren Williams",
        "Team": "LAR",
        "Position": "RB",
        "Position Rank": 12,
        "ADP": 24.2
    },
    {
        "Rank": 36,
        "Name": "Jalen Hurts",
        "Team": "PHI",
        "Position": "QB",
        "Position Rank": 4,
        "ADP": 35.5
    },
    {
        "Rank": 37,
        "Name": "Marvin Harrison Jr.",
        "Team": "ARI",
        "Position": "WR",
        "Position Rank": 18,
        "ADP": 40.8
    },
    {
        "Rank": 38,
        "Name": "Terry McLaurin",
        "Team": "WAS",
        "Position": "WR",
        "Position Rank": 19,
        "ADP": 41.2
    },
    {
        "Rank": 39,
        "Name": "DJ Moore",
        "Team": "CHI",
        "Position": "WR",
        "Position Rank": 20,
        "ADP": 48.8
    },
    {
        "Rank": 40,
        "Name": "Alvin Kamara",
        "Team": "NO",
        "Position": "RB",
        "Position Rank": 13,
        "ADP": 37.2
    },
    {
        "Rank": 41,
        "Name": "James Cook",
        "Team": "BUF",
        "Position": "RB",
        "Position Rank": 14,
        "ADP": 29.8
    },
    {
        "Rank": 42,
        "Name": "Kenneth Walker III",
        "Team": "SEA",
        "Position": "RB",
        "Position Rank": 15,
        "ADP": 40.5
    },
    {
        "Rank": 43,
        "Name": "Omarion Hampton",
        "Team": "LAC",
        "Position": "RB",
        "Position Rank": 16,
        "ADP": 37.3
    },
    {
        "Rank": 44,
        "Name": "Courtland Sutton",
        "Team": "DEN",
        "Position": "WR",
        "Position Rank": 21,
        "ADP": 52.7
    },
    {
        "Rank": 45,
        "Name": "DK Metcalf",
        "Team": "PIT",
        "Position": "WR",
        "Position Rank": 22,
        "ADP": 49.5
    },
    {
        "Rank": 46,
        "Name": "Breece Hall",
        "Team": "NYJ",
        "Position": "RB",
        "Position Rank": 17,
        "ADP": 36.8
    },
    {
        "Rank": 47,
        "Name": "Joe Burrow",
        "Team": "CIN",
        "Position": "QB",
        "Position Rank": 5,
        "ADP": 33.8
    },
    {
        "Rank": 48,
        "Name": "DeVonta Smith",
        "Team": "PHI",
        "Position": "WR",
        "Position Rank": 23,
        "ADP": 56.5
    },
    {
        "Rank": 49,
        "Name": "Tetairoa McMillan",
        "Team": "CAR",
        "Position": "WR",
        "Position Rank": 24,
        "ADP": 63.5
    },
    {
        "Rank": 50,
        "Name": "Chuba Hubbard",
        "Team": "CAR",
        "Position": "RB",
        "Position Rank": 18,
        "ADP": 45.5
    },
    {
        "Rank": 51,
        "Name": "James Conner",
        "Team": "ARI",
        "Position": "RB",
        "Position Rank": 19,
        "ADP": 47.8
    },
    {
        "Rank": 52,
        "Name": "TreVeyon Henderson",
        "Team": "NE",
        "Position": "RB",
        "Position Rank": 20,
        "ADP": 48.2
    },
    {
        "Rank": 53,
        "Name": "Xavier Worthy",
        "Team": "KC",
        "Position": "WR",
        "Position Rank": 25,
        "ADP": 55.3
    },
    {
        "Rank": 54,
        "Name": "Jaylen Waddle",
        "Team": "MIA",
        "Position": "WR",
        "Position Rank": 26,
        "ADP": 72.0
    },
    {
        "Rank": 55,
        "Name": "Calvin Ridley",
        "Team": "TEN",
        "Position": "WR",
        "Position Rank": 27,
        "ADP": 64.2
    },
    {
        "Rank": 56,
        "Name": "Zay Flowers",
        "Team": "BAL",
        "Position": "WR",
        "Position Rank": 28,
        "ADP": 61.7
    },
    {
        "Rank": 57,
        "Name": "George Pickens",
        "Team": "DAL",
        "Position": "WR",
        "Position Rank": 29,
        "ADP": 64.3
    },
    {
        "Rank": 58,
        "Name": "Jameson Williams",
        "Team": "DET",
        "Position": "WR",
        "Position Rank": 30,
        "ADP": 59.8
    },
    {
        "Rank": 59,
        "Name": "D'Andre Swift",
        "Team": "CHI",
        "Position": "RB",
        "Position Rank": 21,
        "ADP": 58.5
    },
    {
        "Rank": 60,
        "Name": "Tony Pollard",
        "Team": "TEN",
        "Position": "RB",
        "Position Rank": 22,
        "ADP": 67.8
    },
    {
        "Rank": 61,
        "Name": "RJ Harvey",
        "Team": "DEN",
        "Position": "RB",
        "Position Rank": 23,
        "ADP": 63.2
    },
    {
        "Rank": 62,
        "Name": "Patrick Mahomes II",
        "Team": "KC",
        "Position": "QB",
        "Position Rank": 6,
        "ADP": 50.3
    },
    {
        "Rank": 63,
        "Name": "T.J. Hockenson",
        "Team": "MIN",
        "Position": "TE",
        "Position Rank": 4,
        "ADP": 63.8
    },
    {
        "Rank": 64,
        "Name": "Chris Olave",
        "Team": "NO",
        "Position": "WR",
        "Position Rank": 31,
        "ADP": 81.7
    },
    {
        "Rank": 65,
        "Name": "David Montgomery",
        "Team": "DET",
        "Position": "RB",
        "Position Rank": 24,
        "ADP": 59.3
    },
    {
        "Rank": 66,
        "Name": "Aaron Jones Sr.",
        "Team": "MIN",
        "Position": "RB",
        "Position Rank": 25,
        "ADP": 64.7
    },
    {
        "Rank": 67,
        "Name": "Isiah Pacheco",
        "Team": "KC",
        "Position": "RB",
        "Position Rank": 26,
        "ADP": 63.0
    },
    {
        "Rank": 68,
        "Name": "Travis Hunter",
        "Team": "JAC",
        "Position": "WR",
        "Position Rank": 32,
        "ADP": 69.2
    },
    {
        "Rank": 69,
        "Name": "Rashee Rice",
        "Team": "KC",
        "Position": "WR",
        "Position Rank": 33,
        "ADP": 60.2
    },
    {
        "Rank": 70,
        "Name": "Baker Mayfield",
        "Team": "TB",
        "Position": "QB",
        "Position Rank": 7,
        "ADP": 63.7
    },
    {
        "Rank": 71,
        "Name": "Sam LaPorta",
        "Team": "DET",
        "Position": "TE",
        "Position Rank": 5,
        "ADP": 52.8
    },
    {
        "Rank": 72,
        "Name": "Jerry Jeudy",
        "Team": "CLE",
        "Position": "WR",
        "Position Rank": 34,
        "ADP": 74.8
    },
    {
        "Rank": 73,
        "Name": "Bo Nix",
        "Team": "DEN",
        "Position": "QB",
        "Position Rank": 8,
        "ADP": 71.8
    },
    {
        "Rank": 74,
        "Name": "Travis Kelce",
        "Team": "KC",
        "Position": "TE",
        "Position Rank": 6,
        "ADP": 62.8
    },
    {
        "Rank": 75,
        "Name": "Rome Odunze",
        "Team": "CHI",
        "Position": "WR",
        "Position Rank": 35,
        "ADP": 81.5
    },
    {
        "Rank": 76,
        "Name": "Stefon Diggs",
        "Team": "NE",
        "Position": "WR",
        "Position Rank": 36,
        "ADP": 86.3
    },
    {
        "Rank": 77,
        "Name": "Jakobi Meyers",
        "Team": "LV",
        "Position": "WR",
        "Position Rank": 37,
        "ADP": 86.8
    },
    {
        "Rank": 78,
        "Name": "Tyrone Tracy Jr.",
        "Team": "NYG",
        "Position": "RB",
        "Position Rank": 27,
        "ADP": 83.7
    },
    {
        "Rank": 79,
        "Name": "Jaylen Warren",
        "Team": "PIT",
        "Position": "RB",
        "Position Rank": 28,
        "ADP": 88.5
    },
    {
        "Rank": 80,
        "Name": "Kyler Murray",
        "Team": "ARI",
        "Position": "QB",
        "Position Rank": 9,
        "ADP": 87.0
    },
    {
        "Rank": 81,
        "Name": "Emeka Egbuka",
        "Team": "TB",
        "Position": "WR",
        "Position Rank": 38,
        "ADP": 96.3
    },
    {
        "Rank": 82,
        "Name": "Ricky Pearsall",
        "Team": "SF",
        "Position": "WR",
        "Position Rank": 39,
        "ADP": 93.8
    },
    {
        "Rank": 83,
        "Name": "Dak Prescott",
        "Team": "DAL",
        "Position": "QB",
        "Position Rank": 10,
        "ADP": 102.5
    },
    {
        "Rank": 84,
        "Name": "David Njoku",
        "Team": "CLE",
        "Position": "TE",
        "Position Rank": 7,
        "ADP": 86.0
    },
    {
        "Rank": 85,
        "Name": "Evan Engram",
        "Team": "DEN",
        "Position": "TE",
        "Position Rank": 8,
        "ADP": 83.8
    },
    {
        "Rank": 86,
        "Name": "Kaleb Johnson",
        "Team": "PIT",
        "Position": "RB",
        "Position Rank": 29,
        "ADP": 79.0
    },
    {
        "Rank": 87,
        "Name": "Mark Andrews",
        "Team": "BAL",
        "Position": "TE",
        "Position Rank": 9,
        "ADP": 73.7
    },
    {
        "Rank": 88,
        "Name": "Travis Etienne Jr.",
        "Team": "JAC",
        "Position": "RB",
        "Position Rank": 30,
        "ADP": 99.0
    },
    {
        "Rank": 89,
        "Name": "Brock Purdy",
        "Team": "SF",
        "Position": "QB",
        "Position Rank": 11,
        "ADP": 100.2
    },
    {
        "Rank": 90,
        "Name": "Khalil Shakir",
        "Team": "BUF",
        "Position": "WR",
        "Position Rank": 40,
        "ADP": 102.0
    },
    {
        "Rank": 91,
        "Name": "Justin Fields",
        "Team": "NYJ",
        "Position": "QB",
        "Position Rank": 12,
        "ADP": 112.0
    },
    {
        "Rank": 92,
        "Name": "Jordan Addison",
        "Team": "MIN",
        "Position": "WR",
        "Position Rank": 41,
        "ADP": 94.0
    },
    {
        "Rank": 93,
        "Name": "Jauan Jennings",
        "Team": "SF",
        "Position": "WR",
        "Position Rank": 42,
        "ADP": 104.7
    },
    {
        "Rank": 94,
        "Name": "Zach Charbonnet",
        "Team": "SEA",
        "Position": "RB",
        "Position Rank": 31,
        "ADP": 115.0
    },
    {
        "Rank": 95,
        "Name": "Michael Pittman Jr.",
        "Team": "IND",
        "Position": "WR",
        "Position Rank": 43,
        "ADP": 115.3
    },
    {
        "Rank": 96,
        "Name": "Deebo Samuel Sr.",
        "Team": "WAS",
        "Position": "WR",
        "Position Rank": 44,
        "ADP": 83.7
    },
    {
        "Rank": 97,
        "Name": "Justin Herbert",
        "Team": "LAC",
        "Position": "QB",
        "Position Rank": 13,
        "ADP": 112.8
    },
    {
        "Rank": 98,
        "Name": "Josh Downs",
        "Team": "IND",
        "Position": "WR",
        "Position Rank": 45,
        "ADP": 127.5
    },
    {
        "Rank": 99,
        "Name": "Caleb Williams",
        "Team": "CHI",
        "Position": "QB",
        "Position Rank": 14,
        "ADP": 120.2
    },
    {
        "Rank": 100,
        "Name": "Javonte Williams",
        "Team": "DAL",
        "Position": "RB",
        "Position Rank": 32,
        "ADP": 112.3
    },
    {
        "Rank": 101,
        "Name": "Drake Maye",
        "Team": "NE",
        "Position": "QB",
        "Position Rank": 15,
        "ADP": 132.0
    },
    {
        "Rank": 102,
        "Name": "Jordan Mason",
        "Team": "MIN",
        "Position": "RB",
        "Position Rank": 33,
        "ADP": 105.8
    },
    {
        "Rank": 103,
        "Name": "Cooper Kupp",
        "Team": "SEA",
        "Position": "WR",
        "Position Rank": 46,
        "ADP": 89.0
    },
    {
        "Rank": 104,
        "Name": "Matthew Golden",
        "Team": "GB",
        "Position": "WR",
        "Position Rank": 47,
        "ADP": 94.8
    },
    {
        "Rank": 105,
        "Name": "Jared Goff",
        "Team": "DET",
        "Position": "QB",
        "Position Rank": 16,
        "ADP": 103.0
    },
    {
        "Rank": 106,
        "Name": "Tyler Warren",
        "Team": "IND",
        "Position": "TE",
        "Position Rank": 10,
        "ADP": 93.5
    },
    {
        "Rank": 107,
        "Name": "Tucker Kraft",
        "Team": "GB",
        "Position": "TE",
        "Position Rank": 11,
        "ADP": 113.2
    },
    {
        "Rank": 108,
        "Name": "Chris Godwin Jr.",
        "Team": "TB",
        "Position": "WR",
        "Position Rank": 48,
        "ADP": 99.5
    },
    {
        "Rank": 109,
        "Name": "J.K. Dobbins",
        "Team": "DEN",
        "Position": "RB",
        "Position Rank": 34,
        "ADP": 108.5
    },
    {
        "Rank": 110,
        "Name": "Jayden Reed",
        "Team": "GB",
        "Position": "WR",
        "Position Rank": 49,
        "ADP": 119.3
    },
    {
        "Rank": 111,
        "Name": "Jordan Love",
        "Team": "GB",
        "Position": "QB",
        "Position Rank": 17,
        "ADP": 140.2
    },
    {
        "Rank": 112,
        "Name": "Jake Ferguson",
        "Team": "DAL",
        "Position": "TE",
        "Position Rank": 12,
        "ADP": 138.0
    },
    {
        "Rank": 113,
        "Name": "Trevor Lawrence",
        "Team": "JAC",
        "Position": "QB",
        "Position Rank": 18,
        "ADP": 159.0
    },
    {
        "Rank": 114,
        "Name": "Rhamondre Stevenson",
        "Team": "NE",
        "Position": "RB",
        "Position Rank": 35,
        "ADP": 114.0
    },
    {
        "Rank": 115,
        "Name": "C.J. Stroud",
        "Team": "HOU",
        "Position": "QB",
        "Position Rank": 19,
        "ADP": 131.5
    },
    {
        "Rank": 116,
        "Name": "Austin Ekeler",
        "Team": "WAS",
        "Position": "RB",
        "Position Rank": 36,
        "ADP": 123.3
    },
    {
        "Rank": 117,
        "Name": "J.J. McCarthy",
        "Team": "MIN",
        "Position": "QB",
        "Position Rank": 20,
        "ADP": 143.2
    },
    {
        "Rank": 118,
        "Name": "Jacory Croskey-Merritt",
        "Team": "WAS",
        "Position": "RB",
        "Position Rank": 37,
        "ADP": 118.0
    },
    {
        "Rank": 119,
        "Name": "Tank Bigsby",
        "Team": "JAC",
        "Position": "RB",
        "Position Rank": 38,
        "ADP": 135.3
    },
    {
        "Rank": 120,
        "Name": "Dalton Kincaid",
        "Team": "BUF",
        "Position": "TE",
        "Position Rank": 13,
        "ADP": 129.2
    },
    {
        "Rank": 121,
        "Name": "Cam Skattebo",
        "Team": "NYG",
        "Position": "RB",
        "Position Rank": 39,
        "ADP": 105.2
    },
    {
        "Rank": 122,
        "Name": "Darnell Mooney",
        "Team": "ATL",
        "Position": "WR",
        "Position Rank": 50,
        "ADP": 143.2
    },
    {
        "Rank": 123,
        "Name": "Keon Coleman",
        "Team": "BUF",
        "Position": "WR",
        "Position Rank": 51,
        "ADP": 122.3
    },
    {
        "Rank": 124,
        "Name": "Dallas Goedert",
        "Team": "PHI",
        "Position": "TE",
        "Position Rank": 14,
        "ADP": 141.3
    },
    {
        "Rank": 125,
        "Name": "Rachaad White",
        "Team": "TB",
        "Position": "RB",
        "Position Rank": 40,
        "ADP": 142.7
    },
    {
        "Rank": 126,
        "Name": "Colston Loveland",
        "Team": "CHI",
        "Position": "TE",
        "Position Rank": 15,
        "ADP": 114.3
    },
    {
        "Rank": 127,
        "Name": "Tyjae Spears",
        "Team": "TEN",
        "Position": "RB",
        "Position Rank": 41,
        "ADP": 144.8
    },
    {
        "Rank": 128,
        "Name": "Joe Mixon",
        "Team": "HOU",
        "Position": "RB",
        "Position Rank": 42,
        "ADP": 77.0
    },
    {
        "Rank": 129,
        "Name": "Christian Kirk",
        "Team": "HOU",
        "Position": "WR",
        "Position Rank": 52,
        "ADP": 153.8
    },
    {
        "Rank": 130,
        "Name": "Rashid Shaheed",
        "Team": "NO",
        "Position": "WR",
        "Position Rank": 53,
        "ADP": 146.8
    },
    {
        "Rank": 131,
        "Name": "Tua Tagovailoa",
        "Team": "MIA",
        "Position": "QB",
        "Position Rank": 21,
        "ADP": 172.3
    },
    {
        "Rank": 132,
        "Name": "Braelon Allen",
        "Team": "NYJ",
        "Position": "RB",
        "Position Rank": 43,
        "ADP": 149.2
    },
    {
        "Rank": 133,
        "Name": "Brandon Aiyuk",
        "Team": "SF",
        "Position": "WR",
        "Position Rank": 54,
        "ADP": 140.5
    },
    {
        "Rank": 134,
        "Name": "Quinshon Judkins",
        "Team": "CLE",
        "Position": "RB",
        "Position Rank": 44,
        "ADP": 100.7
    },
    {
        "Rank": 135,
        "Name": "Bryce Young",
        "Team": "CAR",
        "Position": "QB",
        "Position Rank": 22,
        "ADP": 184.0
    },
    {
        "Rank": 136,
        "Name": "Najee Harris",
        "Team": "LAC",
        "Position": "RB",
        "Position Rank": 45,
        "ADP": 136.8
    },
    {
        "Rank": 137,
        "Name": "Trey Benson",
        "Team": "ARI",
        "Position": "RB",
        "Position Rank": 46,
        "ADP": 160.7
    },
    {
        "Rank": 138,
        "Name": "Michael Penix Jr.",
        "Team": "ATL",
        "Position": "QB",
        "Position Rank": 23,
        "ADP": 183.2
    },
    {
        "Rank": 139,
        "Name": "Luther Burden III",
        "Team": "CHI",
        "Position": "WR",
        "Position Rank": 55,
        "ADP": 169.8
    },
    {
        "Rank": 140,
        "Name": "Ray Davis",
        "Team": "BUF",
        "Position": "RB",
        "Position Rank": 47,
        "ADP": 173.0
    },
    {
        "Rank": 141,
        "Name": "Cedric Tillman",
        "Team": "CLE",
        "Position": "WR",
        "Position Rank": 56,
        "ADP": 202.3
    },
    {
        "Rank": 142,
        "Name": "Hunter Henry",
        "Team": "NE",
        "Position": "TE",
        "Position Rank": 16,
        "ADP": 167.5
    },
    {
        "Rank": 143,
        "Name": "Marvin Mims Jr.",
        "Team": "DEN",
        "Position": "WR",
        "Position Rank": 57,
        "ADP": 151.5
    },
    {
        "Rank": 144,
        "Name": "Jaydon Blue",
        "Team": "DAL",
        "Position": "RB",
        "Position Rank": 48,
        "ADP": 140.3
    },
    {
        "Rank": 145,
        "Name": "Matthew Stafford",
        "Team": "LAR",
        "Position": "QB",
        "Position Rank": 24,
        "ADP": 186.2
    },
    {
        "Rank": 146,
        "Name": "Jayden Higgins",
        "Team": "HOU",
        "Position": "WR",
        "Position Rank": 58,
        "ADP": 147.2
    },
    {
        "Rank": 147,
        "Name": "Kyle Pitts Sr.",
        "Team": "ATL",
        "Position": "TE",
        "Position Rank": 17,
        "ADP": 134.8
    },
    {
        "Rank": 148,
        "Name": "Brian Robinson Jr.",
        "Team": "SF",
        "Position": "RB",
        "Position Rank": 49,
        "ADP": 114.8
    },
    {
        "Rank": 149,
        "Name": "Rashod Bateman",
        "Team": "BAL",
        "Position": "WR",
        "Position Rank": 59,
        "ADP": 173.8
    },
    {
        "Rank": 150,
        "Name": "Jerome Ford",
        "Team": "CLE",
        "Position": "RB",
        "Position Rank": 50,
        "ADP": 168.3
    },
    {
        "Rank": 151,
        "Name": "Geno Smith",
        "Team": "LV",
        "Position": "QB",
        "Position Rank": 25,
        "ADP": 196.3
    },
    {
        "Rank": 152,
        "Name": "Wan'Dale Robinson",
        "Team": "NYG",
        "Position": "WR",
        "Position Rank": 60,
        "ADP": 189.0
    },
    {
        "Rank": 153,
        "Name": "Tyler Allgeier",
        "Team": "ATL",
        "Position": "RB",
        "Position Rank": 51,
        "ADP": 167.8
    },
    {
        "Rank": 154,
        "Name": "Bhayshul Tuten",
        "Team": "JAC",
        "Position": "RB",
        "Position Rank": 52,
        "ADP": 158.7
    },
    {
        "Rank": 155,
        "Name": "Keenan Allen",
        "Team": "LAC",
        "Position": "WR",
        "Position Rank": 61,
        "ADP": 153.0
    },
    {
        "Rank": 156,
        "Name": "Denver Broncos",
        "Team": "DEN",
        "Position": "DST",
        "Position Rank": 1,
        "ADP": 107.8
    },
    {
        "Rank": 157,
        "Name": "Dylan Sampson",
        "Team": "CLE",
        "Position": "RB",
        "Position Rank": 53,
        "ADP": 184.4
    },
    {
        "Rank": 158,
        "Name": "Jonnu Smith",
        "Team": "PIT",
        "Position": "TE",
        "Position Rank": 18,
        "ADP": 146.0
    },
    {
        "Rank": 159,
        "Name": "Zach Ertz",
        "Team": "WAS",
        "Position": "TE",
        "Position Rank": 19,
        "ADP": 154.7
    },
    {
        "Rank": 160,
        "Name": "Nick Chubb",
        "Team": "HOU",
        "Position": "RB",
        "Position Rank": 54,
        "ADP": 148.2
    },
    {
        "Rank": 161,
        "Name": "Marquise Brown",
        "Team": "KC",
        "Position": "WR",
        "Position Rank": 62,
        "ADP": 167.8
    },
    {
        "Rank": 162,
        "Name": "Romeo Doubs",
        "Team": "GB",
        "Position": "WR",
        "Position Rank": 63,
        "ADP": 203.6
    },
    {
        "Rank": 163,
        "Name": "DeMario Douglas",
        "Team": "NE",
        "Position": "WR",
        "Position Rank": 64,
        "ADP": 207.8
    },
    {
        "Rank": 164,
        "Name": "Philadelphia Eagles",
        "Team": "PHI",
        "Position": "DST",
        "Position Rank": 2,
        "ADP": 114.8
    },
    {
        "Rank": 165,
        "Name": "Rico Dowdle",
        "Team": "CAR",
        "Position": "RB",
        "Position Rank": 55,
        "ADP": 184.8
    },
    {
        "Rank": 166,
        "Name": "Cam Ward",
        "Team": "TEN",
        "Position": "QB",
        "Position Rank": 26,
        "ADP": 176.7
    },
    {
        "Rank": 167,
        "Name": "Sam Darnold",
        "Team": "SEA",
        "Position": "QB",
        "Position Rank": 27,
        "ADP": 204.2
    },
    {
        "Rank": 168,
        "Name": "Adam Thielen",
        "Team": "CAR",
        "Position": "WR",
        "Position Rank": 65,
        "ADP": 174.5
    },
    {
        "Rank": 169,
        "Name": "Pittsburgh Steelers",
        "Team": "PIT",
        "Position": "DST",
        "Position Rank": 3,
        "ADP": 134.2
    },
    {
        "Rank": 170,
        "Name": "Kyle Williams",
        "Team": "NE",
        "Position": "WR",
        "Position Rank": 66,
        "ADP": 193.3
    },
    {
        "Rank": 171,
        "Name": "Brenton Strange",
        "Team": "JAC",
        "Position": "TE",
        "Position Rank": 20,
        "ADP": 198.8
    },
    {
        "Rank": 172,
        "Name": "Joshua Palmer",
        "Team": "BUF",
        "Position": "WR",
        "Position Rank": 67,
        "ADP": 197.8
    },
    {
        "Rank": 173,
        "Name": "Baltimore Ravens",
        "Team": "BAL",
        "Position": "DST",
        "Position Rank": 4,
        "ADP": 122.2
    },
    {
        "Rank": 174,
        "Name": "Tre' Harris",
        "Team": "LAC",
        "Position": "WR",
        "Position Rank": 68,
        "ADP": 158.0
    },
    {
        "Rank": 175,
        "Name": "Minnesota Vikings",
        "Team": "MIN",
        "Position": "DST",
        "Position Rank": 5,
        "ADP": 145.0
    },
    {
        "Rank": 176,
        "Name": "Xavier Legette",
        "Team": "CAR",
        "Position": "WR",
        "Position Rank": 69,
        "ADP": 184.2
    },
    {
        "Rank": 177,
        "Name": "Isaac Guerendo",
        "Team": "SF",
        "Position": "RB",
        "Position Rank": 56,
        "ADP": 169.3
    },
    {
        "Rank": 178,
        "Name": "Houston Texans",
        "Team": "HOU",
        "Position": "DST",
        "Position Rank": 6,
        "ADP": 138.5
    },
    {
        "Rank": 179,
        "Name": "Buffalo Bills",
        "Team": "BUF",
        "Position": "DST",
        "Position Rank": 7,
        "ADP": 137.0
    },
    {
        "Rank": 180,
        "Name": "Kansas City Chiefs",
        "Team": "KC",
        "Position": "DST",
        "Position Rank": 8,
        "ADP": 172.3
    },
    {
        "Rank": 181,
        "Name": "Quentin Johnston",
        "Team": "LAC",
        "Position": "WR",
        "Position Rank": 70,
        "ADP": 229.8
    },
    {
        "Rank": 182,
        "Name": "Chig Okonkwo",
        "Team": "TEN",
        "Position": "TE",
        "Position Rank": 21,
        "ADP": 203.8
    },
    {
        "Rank": 183,
        "Name": "Brandon Aubrey",
        "Team": "DAL",
        "Position": "K",
        "Position Rank": 1,
        "ADP": 107.2
    },
    {
        "Rank": 184,
        "Name": "Jaylen Wright",
        "Team": "MIA",
        "Position": "RB",
        "Position Rank": 57,
        "ADP": 190.3
    },
    {
        "Rank": 185,
        "Name": "Detroit Lions",
        "Team": "DET",
        "Position": "DST",
        "Position Rank": 9,
        "ADP": 166.2
    },
    {
        "Rank": 186,
        "Name": "Roschon Johnson",
        "Team": "CHI",
        "Position": "RB",
        "Position Rank": 58,
        "ADP": 231.4
    },
    {
        "Rank": 187,
        "Name": "Jake Bates",
        "Team": "DET",
        "Position": "K",
        "Position Rank": 2,
        "ADP": 129.8
    },
    {
        "Rank": 188,
        "Name": "Cameron Dicker",
        "Team": "LAC",
        "Position": "K",
        "Position Rank": 3,
        "ADP": 134.3
    },
    {
        "Rank": 189,
        "Name": "Woody Marks",
        "Team": "HOU",
        "Position": "RB",
        "Position Rank": 59,
        "ADP": 253.5
    },
    {
        "Rank": 190,
        "Name": "Seattle Seahawks",
        "Team": "SEA",
        "Position": "DST",
        "Position Rank": 10,
        "ADP": 196.7
    },
    {
        "Rank": 191,
        "Name": "Blake Corum",
        "Team": "LAR",
        "Position": "RB",
        "Position Rank": 60,
        "ADP": 221.0
    },
    {
        "Rank": 192,
        "Name": "Los Angeles Rams",
        "Team": "LAR",
        "Position": "DST",
        "Position Rank": 11,
        "ADP": 215.7
    },
    {
        "Rank": 193,
        "Name": "DeAndre Hopkins",
        "Team": "BAL",
        "Position": "WR",
        "Position Rank": 71,
        "ADP": 191.0
    },
    {
        "Rank": 194,
        "Name": "Mike Gesicki",
        "Team": "CIN",
        "Position": "TE",
        "Position Rank": 22,
        "ADP": 235.3
    },
    {
        "Rank": 195,
        "Name": "Aaron Rodgers",
        "Team": "PIT",
        "Position": "QB",
        "Position Rank": 28,
        "ADP": 205.2
    },
    {
        "Rank": 196,
        "Name": "Wil Lutz",
        "Team": "DEN",
        "Position": "K",
        "Position Rank": 4,
        "ADP": 191.3
    },
    {
        "Rank": 197,
        "Name": "Los Angeles Chargers",
        "Team": "LAC",
        "Position": "DST",
        "Position Rank": 12,
        "ADP": 207.5
    },
    {
        "Rank": 198,
        "Name": "Jalen Coker",
        "Team": "CAR",
        "Position": "WR",
        "Position Rank": 72,
        "ADP": 272.0
    },
    {
        "Rank": 199,
        "Name": "Chase McLaughlin",
        "Team": "TB",
        "Position": "K",
        "Position Rank": 5,
        "ADP": 144.7
    },
    {
        "Rank": 200,
        "Name": "Pat Freiermuth",
        "Team": "PIT",
        "Position": "TE",
        "Position Rank": 23,
        "ADP": 203.4
    },
    {
        "Rank": 201,
        "Name": "Ka'imi Fairbairn",
        "Team": "HOU",
        "Position": "K",
        "Position Rank": 6,
        "ADP": 168.3
    },
    {
        "Rank": 202,
        "Name": "Cade Otton",
        "Team": "TB",
        "Position": "TE",
        "Position Rank": 24,
        "ADP": 199.6
    },
    {
        "Rank": 203,
        "Name": "Green Bay Packers",
        "Team": "GB",
        "Position": "DST",
        "Position Rank": 13,
        "ADP": 194.8
    },
    {
        "Rank": 204,
        "Name": "Ollie Gordon II",
        "Team": "MIA",
        "Position": "RB",
        "Position Rank": 61,
        "ADP": 216.7
    },
    {
        "Rank": 205,
        "Name": "Chris Boswell",
        "Team": "PIT",
        "Position": "K",
        "Position Rank": 7,
        "ADP": 155.2
    },
    {
        "Rank": 206,
        "Name": "Harrison Butker",
        "Team": "KC",
        "Position": "K",
        "Position Rank": 8,
        "ADP": 172.5
    },
    {
        "Rank": 207,
        "Name": "Michael Wilson",
        "Team": "ARI",
        "Position": "WR",
        "Position Rank": 73,
        "ADP": 281.5
    },
    {
        "Rank": 208,
        "Name": "Isaiah Likely",
        "Team": "BAL",
        "Position": "TE",
        "Position Rank": 25,
        "ADP": 189.2
    },
    {
        "Rank": 209,
        "Name": "Alec Pierce",
        "Team": "IND",
        "Position": "WR",
        "Position Rank": 74,
        "ADP": 234.3
    },
    {
        "Rank": 210,
        "Name": "Will Shipley",
        "Team": "PHI",
        "Position": "RB",
        "Position Rank": 62,
        "ADP": 234.0
    },
    {
        "Rank": 211,
        "Name": "Tyler Bass",
        "Team": "BUF",
        "Position": "K",
        "Position Rank": 9,
        "ADP": 179.7
    },
    {
        "Rank": 212,
        "Name": "Jack Bech",
        "Team": "LV",
        "Position": "WR",
        "Position Rank": 75,
        "ADP": 208.0
    },
    {
        "Rank": 213,
        "Name": "Justice Hill",
        "Team": "BAL",
        "Position": "RB",
        "Position Rank": 63,
        "ADP": 216.8
    },
    {
        "Rank": 214,
        "Name": "Adonai Mitchell",
        "Team": "IND",
        "Position": "WR",
        "Position Rank": 76,
        "ADP": 280.3
    },
    {
        "Rank": 215,
        "Name": "Mason Taylor",
        "Team": "NYJ",
        "Position": "TE",
        "Position Rank": 26,
        "ADP": 231.5
    },
    {
        "Rank": 216,
        "Name": "Evan McPherson",
        "Team": "CIN",
        "Position": "K",
        "Position Rank": 10,
        "ADP": 205.8
    },
    {
        "Rank": 217,
        "Name": "San Francisco 49ers",
        "Team": "SF",
        "Position": "DST",
        "Position Rank": 14,
        "ADP": 166.5
    },
    {
        "Rank": 218,
        "Name": "New York Jets",
        "Team": "NYJ",
        "Position": "DST",
        "Position Rank": 15,
        "ADP": 227.5
    },
    {
        "Rank": 219,
        "Name": "Jake Elliott",
        "Team": "PHI",
        "Position": "K",
        "Position Rank": 11,
        "ADP": 169.3
    },
    {
        "Rank": 220,
        "Name": "Darius Slayton",
        "Team": "NYG",
        "Position": "WR",
        "Position Rank": 77,
        "ADP": 277.0
    },
    {
        "Rank": 221,
        "Name": "MarShawn Lloyd",
        "Team": "GB",
        "Position": "RB",
        "Position Rank": 64,
        "ADP": 250.6
    },
    {
        "Rank": 222,
        "Name": "Pat Bryant",
        "Team": "DEN",
        "Position": "WR",
        "Position Rank": 78,
        "ADP": 274.5
    },
    {
        "Rank": 223,
        "Name": "Elic Ayomanor",
        "Team": "TEN",
        "Position": "WR",
        "Position Rank": 79,
        "ADP": 258.8
    },
    {
        "Rank": 224,
        "Name": "Kareem Hunt",
        "Team": "KC",
        "Position": "RB",
        "Position Rank": 65,
        "ADP": 198.8
    },
    {
        "Rank": 225,
        "Name": "DJ Giddens",
        "Team": "IND",
        "Position": "RB",
        "Position Rank": 66,
        "ADP": 244.8
    },
    {
        "Rank": 226,
        "Name": "Daniel Jones",
        "Team": "IND",
        "Position": "QB",
        "Position Rank": 29,
        "ADP": 262.2
    },
    {
        "Rank": 227,
        "Name": "Kyle Monangai",
        "Team": "CHI",
        "Position": "RB",
        "Position Rank": 67,
        "ADP": 251.5
    },
    {
        "Rank": 228,
        "Name": "Andrei Iosivas",
        "Team": "CIN",
        "Position": "WR",
        "Position Rank": 80,
        "ADP": 265.0
    },
    {
        "Rank": 229,
        "Name": "Jalen McMillan",
        "Team": "TB",
        "Position": "WR",
        "Position Rank": 81,
        "ADP": 233.5
    },
    {
        "Rank": 230,
        "Name": "Jaylin Noel",
        "Team": "HOU",
        "Position": "WR",
        "Position Rank": 82,
        "ADP": 270.8
    },
    {
        "Rank": 231,
        "Name": "Kendre Miller",
        "Team": "NO",
        "Position": "RB",
        "Position Rank": 68,
        "ADP": 256.0
    },
    {
        "Rank": 232,
        "Name": "Tyler Lockett",
        "Team": "TEN",
        "Position": "WR",
        "Position Rank": 83,
        "ADP": 238.7
    },
    {
        "Rank": 233,
        "Name": "Dalton Schultz",
        "Team": "HOU",
        "Position": "TE",
        "Position Rank": 27,
        "ADP": 236.0
    },
    {
        "Rank": 234,
        "Name": "Calvin Austin III",
        "Team": "PIT",
        "Position": "WR",
        "Position Rank": 84,
        "ADP": 266.3
    },
    {
        "Rank": 235,
        "Name": "Chris Rodriguez Jr.",
        "Team": "WAS",
        "Position": "RB",
        "Position Rank": 69,
        "ADP": 317.3
    },
    {
        "Rank": 236,
        "Name": "Matt Gay",
        "Team": "WAS",
        "Position": "K",
        "Position Rank": 12,
        "ADP": 198.6
    },
    {
        "Rank": 237,
        "Name": "Keaton Mitchell",
        "Team": "BAL",
        "Position": "RB",
        "Position Rank": 70,
        "ADP": 243.5
    },
    {
        "Rank": 238,
        "Name": "Dontayvion Wicks",
        "Team": "GB",
        "Position": "WR",
        "Position Rank": 85,
        "ADP": 308.3
    },
    {
        "Rank": 239,
        "Name": "Russell Wilson",
        "Team": "NYG",
        "Position": "QB",
        "Position Rank": 30,
        "ADP": 247.8
    },
    {
        "Rank": 240,
        "Name": "Jason Sanders",
        "Team": "MIA",
        "Position": "K",
        "Position Rank": 13,
        "ADP": 184.5
    },
    {
        "Rank": 241,
        "Name": "Miles Sanders",
        "Team": "DAL",
        "Position": "RB",
        "Position Rank": 71,
        "ADP": 236.0
    },
    {
        "Rank": 242,
        "Name": "Ja'Tavion Sanders",
        "Team": "CAR",
        "Position": "TE",
        "Position Rank": 28,
        "ADP": 313.4
    },
    {
        "Rank": 243,
        "Name": "Dyami Brown",
        "Team": "JAC",
        "Position": "WR",
        "Position Rank": 86,
        "ADP": 279.8
    },
    {
        "Rank": 244,
        "Name": "Juwan Johnson",
        "Team": "NO",
        "Position": "TE",
        "Position Rank": 29,
        "ADP": 277.0
    },
    {
        "Rank": 245,
        "Name": "Younghoe Koo",
        "Team": "ATL",
        "Position": "K",
        "Position Rank": 14,
        "ADP": 213.5
    },
    {
        "Rank": 246,
        "Name": "Dallas Cowboys",
        "Team": "DAL",
        "Position": "DST",
        "Position Rank": 16,
        "ADP": 206.5
    },
    {
        "Rank": 247,
        "Name": "Elijah Arroyo",
        "Team": "SEA",
        "Position": "TE",
        "Position Rank": 30,
        "ADP": 226.0
    },
    {
        "Rank": 248,
        "Name": "Jalen Royals",
        "Team": "KC",
        "Position": "WR",
        "Position Rank": 87,
        "ADP": 322.8
    },
    {
        "Rank": 249,
        "Name": "Dont'e Thornton Jr.",
        "Team": "LV",
        "Position": "WR",
        "Position Rank": 88,
        "ADP": 232.8
    },
    {
        "Rank": 250,
        "Name": "Tahj Brooks",
        "Team": "CIN",
        "Position": "RB",
        "Position Rank": 72,
        "ADP": 289.3
    },
    {
        "Rank": 251,
        "Name": "Brashard Smith",
        "Team": "KC",
        "Position": "RB",
        "Position Rank": 73,
        "ADP": 281.0
    },
    {
        "Rank": 252,
        "Name": "Roman Wilson",
        "Team": "PIT",
        "Position": "WR",
        "Position Rank": 89,
        "ADP": 307.6
    },
    {
        "Rank": 253,
        "Name": "Tory Horton",
        "Team": "SEA",
        "Position": "WR",
        "Position Rank": 90,
        "ADP": 282.2
    },
    {
        "Rank": 254,
        "Name": "Jaleel McLaughlin",
        "Team": "DEN",
        "Position": "RB",
        "Position Rank": 74,
        "ADP": 278.5
    },
    {
        "Rank": 255,
        "Name": "Devaughn Vele",
        "Team": "NO",
        "Position": "WR",
        "Position Rank": 91,
        "ADP": 309.5
    },
    {
        "Rank": 256,
        "Name": "Tampa Bay Buccaneers",
        "Team": "TB",
        "Position": "DST",
        "Position Rank": 17,
        "ADP": 205.0
    },
    {
        "Rank": 257,
        "Name": "Dameon Pierce",
        "Team": "HOU",
        "Position": "RB",
        "Position Rank": 75,
        "ADP": 306.8
    },
    {
        "Rank": 258,
        "Name": "Jarquez Hunter",
        "Team": "LAR",
        "Position": "RB",
        "Position Rank": 76,
        "ADP": 302.5
    },
    {
        "Rank": 259,
        "Name": "Cole Kmet",
        "Team": "CHI",
        "Position": "TE",
        "Position Rank": 31,
        "ADP": 245.5
    },
    {
        "Rank": 260,
        "Name": "Anthony Richardson Sr.",
        "Team": "IND",
        "Position": "QB",
        "Position Rank": 31,
        "ADP": 240.8
    },
    {
        "Rank": 261,
        "Name": "Raheem Mostert",
        "Team": "LV",
        "Position": "RB",
        "Position Rank": 77,
        "ADP": 227.0
    },
    {
        "Rank": 262,
        "Name": "Joe Flacco",
        "Team": "CLE",
        "Position": "QB",
        "Position Rank": 32,
        "ADP": 272.6
    },
    {
        "Rank": 263,
        "Name": "Malik Washington",
        "Team": "MIA",
        "Position": "WR",
        "Position Rank": 92,
        "ADP": 361.0
    },
    {
        "Rank": 264,
        "Name": "Diontae Johnson",
        "Team": "CLE",
        "Position": "WR",
        "Position Rank": 93,
        "ADP": 282.0
    },
    {
        "Rank": 265,
        "Name": "Devin Neal",
        "Team": "NO",
        "Position": "RB",
        "Position Rank": 78,
        "ADP": 340.3
    },
    {
        "Rank": 266,
        "Name": "Sean Tucker",
        "Team": "TB",
        "Position": "RB",
        "Position Rank": 79,
        "ADP": 278.0
    },
    {
        "Rank": 267,
        "Name": "Brandin Cooks",
        "Team": "NO",
        "Position": "WR",
        "Position Rank": 94,
        "ADP": 308.0
    },
    {
        "Rank": 268,
        "Name": "Jalen Tolbert",
        "Team": "DAL",
        "Position": "WR",
        "Position Rank": 95,
        "ADP": 268.0
    },
    {
        "Rank": 269,
        "Name": "Isaac TeSlaa",
        "Team": "DET",
        "Position": "WR",
        "Position Rank": 96,
        "ADP": 248.8
    },
    {
        "Rank": 270,
        "Name": "Elijah Moore",
        "Team": "BUF",
        "Position": "WR",
        "Position Rank": 97,
        "ADP": 304.3
    },
    {
        "Rank": 271,
        "Name": "Joshua Karty",
        "Team": "LAR",
        "Position": "K",
        "Position Rank": 15,
        "ADP": 253.3
    },
    {
        "Rank": 272,
        "Name": "Kayshon Boutte",
        "Team": "NE",
        "Position": "WR",
        "Position Rank": 98,
        "ADP": 320.3
    },
    {
        "Rank": 273,
        "Name": "Trevor Etienne",
        "Team": "CAR",
        "Position": "RB",
        "Position Rank": 80,
        "ADP": 283.5
    },
    {
        "Rank": 274,
        "Name": "Theo Johnson",
        "Team": "NYG",
        "Position": "TE",
        "Position Rank": 32,
        "ADP": 281.3
    },
    {
        "Rank": 275,
        "Name": "Harold Fannin Jr.",
        "Team": "CLE",
        "Position": "TE",
        "Position Rank": 33,
        "ADP": 326.2
    },
    {
        "Rank": 276,
        "Name": "Kenneth Gainwell",
        "Team": "PIT",
        "Position": "RB",
        "Position Rank": 81,
        "ADP": 323.7
    },
    {
        "Rank": 277,
        "Name": "Elijah Mitchell",
        "Team": "KC",
        "Position": "RB",
        "Position Rank": 82,
        "ADP": 256.5
    },
    {
        "Rank": 278,
        "Name": "Nick Westbrook-Ikhine",
        "Team": "MIA",
        "Position": "WR",
        "Position Rank": 99,
        "ADP": 303.5
    },
    {
        "Rank": 279,
        "Name": "Noah Gray",
        "Team": "KC",
        "Position": "TE",
        "Position Rank": 34,
        "ADP": 263.8
    },
    {
        "Rank": 280,
        "Name": "Devin Singletary",
        "Team": "NYG",
        "Position": "RB",
        "Position Rank": 83,
        "ADP": 265.0
    },
    {
        "Rank": 281,
        "Name": "Antonio Gibson",
        "Team": "NE",
        "Position": "RB",
        "Position Rank": 84,
        "ADP": 284.0
    },
    {
        "Rank": 282,
        "Name": "Ty Johnson",
        "Team": "BUF",
        "Position": "RB",
        "Position Rank": 85,
        "ADP": 287.3
    },
    {
        "Rank": 283,
        "Name": "Tre Tucker",
        "Team": "LV",
        "Position": "WR",
        "Position Rank": 100,
        "ADP": 289.7
    },
    {
        "Rank": 284,
        "Name": "Darren Waller",
        "Team": "MIA",
        "Position": "TE",
        "Position Rank": 35,
        "ADP": 205.7
    },
    {
        "Rank": 285,
        "Name": "Jalen Nailor",
        "Team": "MIN",
        "Position": "WR",
        "Position Rank": 101,
        "ADP": 300.3
    },
    {
        "Rank": 286,
        "Name": "Jaxson Dart",
        "Team": "NYG",
        "Position": "QB",
        "Position Rank": 33,
        "ADP": 239.4
    },
    {
        "Rank": 287,
        "Name": "Chicago Bears",
        "Team": "CHI",
        "Position": "DST",
        "Position Rank": 18,
        "ADP": 211.6
    },
    {
        "Rank": 288,
        "Name": "Tyler Shough",
        "Team": "NO",
        "Position": "QB",
        "Position Rank": 34,
        "ADP": 297.3
    },
    {
        "Rank": 289,
        "Name": "Tyler Loop",
        "Team": "BAL",
        "Position": "K",
        "Position Rank": 16,
        "ADP": 190.5
    },
    {
        "Rank": 290,
        "Name": "Audric Estime",
        "Team": "FA",
        "Position": "RB",
        "Position Rank": 86,
        "ADP": 350.5
    },
    {
        "Rank": 291,
        "Name": "Cleveland Browns",
        "Team": "CLE",
        "Position": "DST",
        "Position Rank": 19,
        "ADP": 229.8
    },
    {
        "Rank": 292,
        "Name": "Parker Washington",
        "Team": "JAC",
        "Position": "WR",
        "Position Rank": 102,
        "ADP": 357.5
    },
    {
        "Rank": 293,
        "Name": "Isaiah Davis",
        "Team": "NYJ",
        "Position": "RB",
        "Position Rank": 87,
        "ADP": 493.0
    },
    {
        "Rank": 294,
        "Name": "Will Reichard",
        "Team": "MIN",
        "Position": "K",
        "Position Rank": 17,
        "ADP": 236.6
    },
    {
        "Rank": 295,
        "Name": "Luke McCaffrey",
        "Team": "WAS",
        "Position": "WR",
        "Position Rank": 103,
        "ADP": 283.7
    },
    {
        "Rank": 296,
        "Name": "Tim Patrick",
        "Team": "DET",
        "Position": "WR",
        "Position Rank": 104,
        "ADP": 345.7
    },
    {
        "Rank": 297,
        "Name": "Daniel Carlson",
        "Team": "LV",
        "Position": "K",
        "Position Rank": 18,
        "ADP": 218.6
    },
    {
        "Rank": 298,
        "Name": "Jordan James",
        "Team": "SF",
        "Position": "RB",
        "Position Rank": 88,
        "ADP": 285.5
    },
    {
        "Rank": 299,
        "Name": "Ray-Ray McCloud III",
        "Team": "ATL",
        "Position": "WR",
        "Position Rank": 105,
        "ADP": 281.3
    },
    {
        "Rank": 300,
        "Name": "Taysom Hill",
        "Team": "NO",
        "Position": "TE",
        "Position Rank": 36,
        "ADP": 322.5
    },
    {
        "Rank": 301,
        "Name": "Xavier Restrepo",
        "Team": "TEN",
        "Position": "WR",
        "Position Rank": 106,
        "ADP": 376.0
    },
    {
        "Rank": 302,
        "Name": "New England Patriots",
        "Team": "NE",
        "Position": "DST",
        "Position Rank": 20,
        "ADP": 220.4
    },
    {
        "Rank": 303,
        "Name": "Emanuel Wilson",
        "Team": "GB",
        "Position": "RB",
        "Position Rank": 89,
        "ADP": 336.7
    },
    {
        "Rank": 304,
        "Name": "Terrance Ferguson",
        "Team": "LAR",
        "Position": "TE",
        "Position Rank": 37,
        "ADP": 299.0
    },
    {
        "Rank": 305,
        "Name": "Amari Cooper",
        "Team": "LV",
        "Position": "WR",
        "Position Rank": 107,
        "ADP": 297.7
    },
    {
        "Rank": 306,
        "Name": "Khalil Herbert",
        "Team": "IND",
        "Position": "RB",
        "Position Rank": 90,
        "ADP": 429.7
    },
    {
        "Rank": 307,
        "Name": "Troy Franklin",
        "Team": "DEN",
        "Position": "WR",
        "Position Rank": 108,
        "ADP": 279.6
    },
    {
        "Rank": 308,
        "Name": "Kimani Vidal",
        "Team": "LAC",
        "Position": "RB",
        "Position Rank": 91,
        "ADP": 460.0
    },
    {
        "Rank": 309,
        "Name": "Christian Watson",
        "Team": "GB",
        "Position": "WR",
        "Position Rank": 109,
        "ADP": 335.0
    },
    {
        "Rank": 310,
        "Name": "Arizona Cardinals",
        "Team": "ARI",
        "Position": "DST",
        "Position Rank": 21,
        "ADP": 209.0
    },
    {
        "Rank": 311,
        "Name": "Noah Fant",
        "Team": "CIN",
        "Position": "TE",
        "Position Rank": 38,
        "ADP": 318.3
    },
    {
        "Rank": 312,
        "Name": "Sincere McCormick",
        "Team": "LV",
        "Position": "RB",
        "Position Rank": 92,
        "ADP": 465.0
    },
    {
        "Rank": 313,
        "Name": "Tutu Atwell",
        "Team": "LAR",
        "Position": "WR",
        "Position Rank": 110,
        "ADP": 312.0
    },
    {
        "Rank": 314,
        "Name": "Damien Martinez",
        "Team": "SEA",
        "Position": "RB",
        "Position Rank": 93,
        "ADP": 344.0
    },
    {
        "Rank": 315,
        "Name": "Chris Brooks",
        "Team": "GB",
        "Position": "RB",
        "Position Rank": 94,
        "ADP": 433.0
    },
    {
        "Rank": 316,
        "Name": "Jermaine Burton",
        "Team": "CIN",
        "Position": "WR",
        "Position Rank": 111,
        "ADP": 437.8
    },
    {
        "Rank": 317,
        "Name": "Tyler Higbee",
        "Team": "LAR",
        "Position": "TE",
        "Position Rank": 39,
        "ADP": 292.3
    },
    {
        "Rank": 318,
        "Name": "Phil Mafah",
        "Team": "DAL",
        "Position": "RB",
        "Position Rank": 95,
        "ADP": 579.5
    },
    {
        "Rank": 319,
        "Name": "Tez Johnson",
        "Team": "TB",
        "Position": "WR",
        "Position Rank": 112,
        "ADP": 364.7
    },
    {
        "Rank": 320,
        "Name": "Ty Chandler",
        "Team": "MIN",
        "Position": "RB",
        "Position Rank": 96,
        "ADP": 372.3
    },
    {
        "Rank": 321,
        "Name": "Samaje Perine",
        "Team": "CIN",
        "Position": "RB",
        "Position Rank": 97,
        "ADP": 309.7
    },
    {
        "Rank": 322,
        "Name": "Shedeur Sanders",
        "Team": "CLE",
        "Position": "QB",
        "Position Rank": 35,
        "ADP": 223.5
    },
    {
        "Rank": 323,
        "Name": "Oronde Gadsden II",
        "Team": "LAC",
        "Position": "TE",
        "Position Rank": 40,
        "ADP": 391.3
    },
    {
        "Rank": 324,
        "Name": "Jordan Whittington",
        "Team": "LAR",
        "Position": "WR",
        "Position Rank": 113,
        "ADP": 368.0
    },
    {
        "Rank": 325,
        "Name": "Josh Reynolds",
        "Team": "NYJ",
        "Position": "WR",
        "Position Rank": 114,
        "ADP": 416.5
    },
    {
        "Rank": 326,
        "Name": "Spencer Rattler",
        "Team": "NO",
        "Position": "QB",
        "Position Rank": 36,
        "ADP": 378.5
    },
    {
        "Rank": 327,
        "Name": "Raheim Sanders",
        "Team": "LAC",
        "Position": "RB",
        "Position Rank": 98,
        "ADP": 635.0
    },
    {
        "Rank": 328,
        "Name": "Jason Myers",
        "Team": "SEA",
        "Position": "K",
        "Position Rank": 19,
        "ADP": 232.0
    },
    {
        "Rank": 329,
        "Name": "Zamir White",
        "Team": "LV",
        "Position": "RB",
        "Position Rank": 99,
        "ADP": 313.3
    },
    {
        "Rank": 330,
        "Name": "Tyler Conklin",
        "Team": "LAC",
        "Position": "TE",
        "Position Rank": 41,
        "ADP": 312.8
    },
    {
        "Rank": 331,
        "Name": "Noah Brown",
        "Team": "WAS",
        "Position": "WR",
        "Position Rank": 115,
        "ADP": 390.0
    },
    {
        "Rank": 332,
        "Name": "Ben Sinnott",
        "Team": "WAS",
        "Position": "TE",
        "Position Rank": 42,
        "ADP": 380.3
    },
    {
        "Rank": 333,
        "Name": "Will Dissly",
        "Team": "LAC",
        "Position": "TE",
        "Position Rank": 43,
        "ADP": 353.0
    },
    {
        "Rank": 334,
        "Name": "KaVontae Turpin",
        "Team": "DAL",
        "Position": "WR",
        "Position Rank": 116,
        "ADP": 276.0
    },
    {
        "Rank": 335,
        "Name": "New York Giants",
        "Team": "NYG",
        "Position": "DST",
        "Position Rank": 22,
        "ADP": 221.7
    },
    {
        "Rank": 336,
        "Name": "Brandon McManus",
        "Team": "GB",
        "Position": "K",
        "Position Rank": 20,
        "ADP": 232.0
    },
    {
        "Rank": 337,
        "Name": "A.J. Dillon",
        "Team": "PHI",
        "Position": "RB",
        "Position Rank": 100,
        "ADP": 320.8
    },
    {
        "Rank": 338,
        "Name": "Cam Little",
        "Team": "JAC",
        "Position": "K",
        "Position Rank": 21,
        "ADP": 188.3
    },
    {
        "Rank": 339,
        "Name": "KeAndre Lambert-Smith",
        "Team": "LAC",
        "Position": "WR",
        "Position Rank": 117,
        "ADP": 334.7
    },
    {
        "Rank": 340,
        "Name": "Jalen Milroe",
        "Team": "SEA",
        "Position": "QB",
        "Position Rank": 37,
        "ADP": 286.5
    },
    {
        "Rank": 341,
        "Name": "Demarcus Robinson",
        "Team": "SF",
        "Position": "WR",
        "Position Rank": 118,
        "ADP": 368.0
    },
    {
        "Rank": 342,
        "Name": "Jaylin Lane",
        "Team": "WAS",
        "Position": "WR",
        "Position Rank": 119,
        "ADP": 455.0
    },
    {
        "Rank": 343,
        "Name": "Zack Moss",
        "Team": "FA",
        "Position": "RB",
        "Position Rank": 101,
        "ADP": 272.4
    },
    {
        "Rank": 344,
        "Name": "Gabe Davis",
        "Team": "FA",
        "Position": "WR",
        "Position Rank": 120,
        "ADP": 314.0
    },
    {
        "Rank": 345,
        "Name": "Michael Mayer",
        "Team": "LV",
        "Position": "TE",
        "Position Rank": 44,
        "ADP": 336.3
    },
    {
        "Rank": 346,
        "Name": "Isaiah Bond",
        "Team": "CLE",
        "Position": "WR",
        "Position Rank": 121,
        "ADP": 404.7
    },
    {
        "Rank": 347,
        "Name": "Tai Felton",
        "Team": "MIN",
        "Position": "WR",
        "Position Rank": 122,
        "ADP": 432.0
    },
    {
        "Rank": 348,
        "Name": "Miami Dolphins",
        "Team": "MIA",
        "Position": "DST",
        "Position Rank": 23,
        "ADP": 269.6
    },
    {
        "Rank": 349,
        "Name": "AJ Barner",
        "Team": "SEA",
        "Position": "TE",
        "Position Rank": 45,
        "ADP": 339.5
    },
    {
        "Rank": 350,
        "Name": "Marquez Valdes-Scantling",
        "Team": "SEA",
        "Position": "WR",
        "Position Rank": 123,
        "ADP": 337.0
    },
    {
        "Rank": 351,
        "Name": "John Metchie III",
        "Team": "PHI",
        "Position": "WR",
        "Position Rank": 124,
        "ADP": 355.3
    },
    {
        "Rank": 352,
        "Name": "Dawson Knox",
        "Team": "BUF",
        "Position": "TE",
        "Position Rank": 46,
        "ADP": 287.3
    },
    {
        "Rank": 353,
        "Name": "Jake Moody",
        "Team": "SF",
        "Position": "K",
        "Position Rank": 22,
        "ADP": 244.6
    },
    {
        "Rank": 354,
        "Name": "Olamide Zaccheaus",
        "Team": "CHI",
        "Position": "WR",
        "Position Rank": 125,
        "ADP": 335.3
    },
    {
        "Rank": 355,
        "Name": "Kirk Cousins",
        "Team": "ATL",
        "Position": "QB",
        "Position Rank": 38,
        "ADP": 280.3
    },
    {
        "Rank": 356,
        "Name": "Allen Lazard",
        "Team": "NYJ",
        "Position": "WR",
        "Position Rank": 126,
        "ADP": 313.0
    },
    {
        "Rank": 357,
        "Name": "Cam Akers",
        "Team": "FA",
        "Position": "RB",
        "Position Rank": 102,
        "ADP": 397.3
    },
    {
        "Rank": 358,
        "Name": "Justin Tucker",
        "Team": "FA",
        "Position": "K",
        "Position Rank": 23,
        "ADP": 281.5
    },
    {
        "Rank": 359,
        "Name": "Luke Musgrave",
        "Team": "GB",
        "Position": "TE",
        "Position Rank": 47,
        "ADP": 317.7
    },
    {
        "Rank": 360,
        "Name": "Zay Jones",
        "Team": "ARI",
        "Position": "WR",
        "Position Rank": 127,
        "ADP": 497.0
    },
    {
        "Rank": 361,
        "Name": "Emari Demercado",
        "Team": "ARI",
        "Position": "RB",
        "Position Rank": 103,
        "ADP": 481.0
    },
    {
        "Rank": 362,
        "Name": "Savion Williams",
        "Team": "GB",
        "Position": "WR",
        "Position Rank": 128,
        "ADP": 515.3
    },
    {
        "Rank": 363,
        "Name": "Washington Commanders",
        "Team": "WAS",
        "Position": "DST",
        "Position Rank": 24,
        "ADP": 219.7
    },
    {
        "Rank": 364,
        "Name": "Gunnar Helm",
        "Team": "TEN",
        "Position": "TE",
        "Position Rank": 48,
        "ADP": 429.0
    },
    {
        "Rank": 365,
        "Name": "Chimere Dike",
        "Team": "TEN",
        "Position": "WR",
        "Position Rank": 129,
        "ADP": 672.0
    },
    {
        "Rank": 366,
        "Name": "Curtis Samuel",
        "Team": "BUF",
        "Position": "WR",
        "Position Rank": 130,
        "ADP": 404.7
    },
    {
        "Rank": 367,
        "Name": "Mack Hollins",
        "Team": "NE",
        "Position": "WR",
        "Position Rank": 131,
        "ADP": 378.7
    },
    {
        "Rank": 368,
        "Name": "Austin Hooper",
        "Team": "NE",
        "Position": "TE",
        "Position Rank": 49,
        "ADP": 347.0
    },
    {
        "Rank": 369,
        "Name": "Greg Dortch",
        "Team": "ARI",
        "Position": "WR",
        "Position Rank": 132,
        "ADP": 441.0
    },
    {
        "Rank": 370,
        "Name": "Van Jefferson",
        "Team": "TEN",
        "Position": "WR",
        "Position Rank": 133,
        "ADP": 429.0
    },
    {
        "Rank": 371,
        "Name": "Donovan Edwards",
        "Team": "NYJ",
        "Position": "RB",
        "Position Rank": 104,
        "ADP": 505.0
    },
    {
        "Rank": 372,
        "Name": "Gus Edwards",
        "Team": "FA",
        "Position": "RB",
        "Position Rank": 105,
        "ADP": 515.0
    },
    {
        "Rank": 373,
        "Name": "Jameis Winston",
        "Team": "NYG",
        "Position": "QB",
        "Position Rank": 39,
        "ADP": 303.3
    },
    {
        "Rank": 374,
        "Name": "Kalel Mullings",
        "Team": "TEN",
        "Position": "RB",
        "Position Rank": 106,
        "ADP": 635.5
    },
    {
        "Rank": 375,
        "Name": "LeQuint Allen Jr.",
        "Team": "JAC",
        "Position": "RB",
        "Position Rank": 107,
        "ADP": 585.0
    },
    {
        "Rank": 376,
        "Name": "Hunter Renfrow",
        "Team": "CAR",
        "Position": "WR",
        "Position Rank": 134,
        "ADP": 318.3
    },
    {
        "Rank": 377,
        "Name": "Jimmy Garoppolo",
        "Team": "LAR",
        "Position": "QB",
        "Position Rank": 40,
        "ADP": 358.0
    },
    {
        "Rank": 378,
        "Name": "Kyle Juszczyk",
        "Team": "SF",
        "Position": "RB",
        "Position Rank": 108,
        "ADP": 249.0
    },
    {
        "Rank": 379,
        "Name": "Jahan Dotson",
        "Team": "PHI",
        "Position": "WR",
        "Position Rank": 135,
        "ADP": 324.3
    },
    {
        "Rank": 380,
        "Name": "Trey Sermon",
        "Team": "PIT",
        "Position": "RB",
        "Position Rank": 109,
        "ADP": 431.5
    },
    {
        "Rank": 381,
        "Name": "Dillon Gabriel",
        "Team": "CLE",
        "Position": "QB",
        "Position Rank": 41,
        "ADP": 448.5
    },
    {
        "Rank": 382,
        "Name": "Foster Moreau",
        "Team": "NO",
        "Position": "TE",
        "Position Rank": 50,
        "ADP": 447.5
    },
    {
        "Rank": 383,
        "Name": "Kenny Pickett",
        "Team": "LV",
        "Position": "QB",
        "Position Rank": 42,
        "ADP": 355.0
    },
    {
        "Rank": 384,
        "Name": "Craig Reynolds",
        "Team": "DET",
        "Position": "RB",
        "Position Rank": 110,
        "ADP": 375.0
    },
    {
        "Rank": 385,
        "Name": "Cade Stover",
        "Team": "HOU",
        "Position": "TE",
        "Position Rank": 51,
        "ADP": 444.0
    },
    {
        "Rank": 386,
        "Name": "Tank Dell",
        "Team": "HOU",
        "Position": "WR",
        "Position Rank": 136,
        "ADP": 303.7
    },
    {
        "Rank": 387,
        "Name": "Efton Chism III",
        "Team": "NE",
        "Position": "WR",
        "Position Rank": 137,
        "ADP": 320.3
    },
    {
        "Rank": 388,
        "Name": "Jacob Cowing",
        "Team": "SF",
        "Position": "WR",
        "Position Rank": 138,
        "ADP": 480.0
    },
    {
        "Rank": 389,
        "Name": "Jamari Thrash",
        "Team": "CLE",
        "Position": "WR",
        "Position Rank": 139,
        "ADP": 565.0
    },
    {
        "Rank": 390,
        "Name": "Luke Schoonmaker",
        "Team": "DAL",
        "Position": "TE",
        "Position Rank": 52,
        "ADP": 378.0
    },
    {
        "Rank": 391,
        "Name": "Indianapolis Colts",
        "Team": "IND",
        "Position": "DST",
        "Position Rank": 25,
        "ADP": 266.8
    },
    {
        "Rank": 392,
        "Name": "Robert Woods",
        "Team": "PIT",
        "Position": "WR",
        "Position Rank": 140,
        "ADP": 399.7
    },
    {
        "Rank": 393,
        "Name": "Tommy Tremble",
        "Team": "CAR",
        "Position": "TE",
        "Position Rank": 53,
        "ADP": 457.0
    },
    {
        "Rank": 394,
        "Name": "Tyrod Taylor",
        "Team": "NYJ",
        "Position": "QB",
        "Position Rank": 43,
        "ADP": 487.0
    },
    {
        "Rank": 395,
        "Name": "Chad Ryland",
        "Team": "ARI",
        "Position": "K",
        "Position Rank": 24,
        "ADP": 312.0
    },
    {
        "Rank": 396,
        "Name": "Pierre Strong Jr.",
        "Team": "CLE",
        "Position": "RB",
        "Position Rank": 111,
        "ADP": 524.0
    },
    {
        "Rank": 397,
        "Name": "Cairo Santos",
        "Team": "CHI",
        "Position": "K",
        "Position Rank": 25,
        "ADP": 253.0
    },
    {
        "Rank": 398,
        "Name": "Antwane Wells Jr.",
        "Team": "NYG",
        "Position": "WR",
        "Position Rank": 141
    },
    {
        "Rank": 399,
        "Name": "Theo Wease Jr.",
        "Team": "MIA",
        "Position": "WR",
        "Position Rank": 142
    },
    {
        "Rank": 400,
        "Name": "Josh Oliver",
        "Team": "MIN",
        "Position": "TE",
        "Position Rank": 54,
        "ADP": 370.3
    },
    {
        "Rank": 401,
        "Name": "Blake Grupe",
        "Team": "NO",
        "Position": "K",
        "Position Rank": 26,
        "ADP": 299.0
    },
    {
        "Rank": 402,
        "Name": "JuJu Smith-Schuster",
        "Team": "KC",
        "Position": "WR",
        "Position Rank": 143,
        "ADP": 294.7
    },
    {
        "Rank": 403,
        "Name": "Arian Smith",
        "Team": "NYJ",
        "Position": "WR",
        "Position Rank": 144,
        "ADP": 550.3
    },
    {
        "Rank": 404,
        "Name": "Atlanta Falcons",
        "Team": "ATL",
        "Position": "DST",
        "Position Rank": 26,
        "ADP": 229.0
    },
    {
        "Rank": 405,
        "Name": "Eddy Pineiro",
        "Team": "FA",
        "Position": "K",
        "Position Rank": 27,
        "ADP": 412.0
    },
    {
        "Rank": 406,
        "Name": "Jordan Watkins",
        "Team": "SF",
        "Position": "WR",
        "Position Rank": 145,
        "ADP": 580.0
    },
    {
        "Rank": 407,
        "Name": "Dare Ogunbowale",
        "Team": "HOU",
        "Position": "RB",
        "Position Rank": 112,
        "ADP": 493.0
    },
    {
        "Rank": 408,
        "Name": "Devontez Walker",
        "Team": "BAL",
        "Position": "WR",
        "Position Rank": 146,
        "ADP": 550.5
    },
    {
        "Rank": 409,
        "Name": "Xavier Hutchinson",
        "Team": "HOU",
        "Position": "WR",
        "Position Rank": 147,
        "ADP": 469.0
    },
    {
        "Rank": 410,
        "Name": "Cincinnati Bengals",
        "Team": "CIN",
        "Position": "DST",
        "Position Rank": 27,
        "ADP": 230.8
    },
    {
        "Rank": 411,
        "Name": "Mason Rudolph",
        "Team": "PIT",
        "Position": "QB",
        "Position Rank": 44,
        "ADP": 356.7
    },
    {
        "Rank": 412,
        "Name": "Jeremy McNichols",
        "Team": "WAS",
        "Position": "RB",
        "Position Rank": 113,
        "ADP": 382.0
    },
    {
        "Rank": 413,
        "Name": "Jonathon Brooks",
        "Team": "CAR",
        "Position": "RB",
        "Position Rank": 114,
        "ADP": 733.0
    },
    {
        "Rank": 414,
        "Name": "Graham Gano",
        "Team": "NYG",
        "Position": "K",
        "Position Rank": 28,
        "ADP": 274.7
    },
    {
        "Rank": 415,
        "Name": "Matt Prater",
        "Team": "FA",
        "Position": "K",
        "Position Rank": 29,
        "ADP": 455.5
    },
    {
        "Rank": 416,
        "Name": "Joe Milton III",
        "Team": "DAL",
        "Position": "QB",
        "Position Rank": 45,
        "ADP": 341.0
    },
    {
        "Rank": 417,
        "Name": "Kendrick Bourne",
        "Team": "NE",
        "Position": "WR",
        "Position Rank": 148,
        "ADP": 467.7
    },
    {
        "Rank": 418,
        "Name": "Clyde Edwards-Helaire",
        "Team": "NO",
        "Position": "RB",
        "Position Rank": 115,
        "ADP": 421.0
    },
    {
        "Rank": 419,
        "Name": "Jalin Hyatt",
        "Team": "NYG",
        "Position": "WR",
        "Position Rank": 149,
        "ADP": 374.3
    },
    {
        "Rank": 420,
        "Name": "Grant Calcaterra",
        "Team": "PHI",
        "Position": "TE",
        "Position Rank": 55,
        "ADP": 305.5
    },
    {
        "Rank": 421,
        "Name": "Ja'Quinden Jackson",
        "Team": "JAC",
        "Position": "RB",
        "Position Rank": 116,
        "ADP": 611.0
    },
    {
        "Rank": 422,
        "Name": "Tyler Goodson",
        "Team": "IND",
        "Position": "RB",
        "Position Rank": 117,
        "ADP": 460.0
    },
    {
        "Rank": 423,
        "Name": "Jeremy Ruckert",
        "Team": "NYJ",
        "Position": "TE",
        "Position Rank": 56,
        "ADP": 474.0
    },
    {
        "Rank": 424,
        "Name": "Julius Chestnut",
        "Team": "TEN",
        "Position": "RB",
        "Position Rank": 118,
        "ADP": 425.5
    },
    {
        "Rank": 425,
        "Name": "Alec Ingold",
        "Team": "MIA",
        "Position": "RB",
        "Position Rank": 119,
        "ADP": 502.0
    },
    {
        "Rank": 426,
        "Name": "D'Ernest Johnson",
        "Team": "BAL",
        "Position": "RB",
        "Position Rank": 120
    },
    {
        "Rank": 427,
        "Name": "Jimmy Horn Jr.",
        "Team": "CAR",
        "Position": "WR",
        "Position Rank": 150,
        "ADP": 292.0
    },
    {
        "Rank": 428,
        "Name": "George Holani",
        "Team": "SEA",
        "Position": "RB",
        "Position Rank": 121,
        "ADP": 448.0
    },
    {
        "Rank": 429,
        "Name": "Jonathan Mingo",
        "Team": "DAL",
        "Position": "WR",
        "Position Rank": 151,
        "ADP": 481.3
    },
    {
        "Rank": 430,
        "Name": "Nick Folk",
        "Team": "NYJ",
        "Position": "K",
        "Position Rank": 30,
        "ADP": 283.0
    },
    {
        "Rank": 431,
        "Name": "Skyy Moore",
        "Team": "SF",
        "Position": "WR",
        "Position Rank": 152,
        "ADP": 391.7
    },
    {
        "Rank": 432,
        "Name": "Deshaun Watson",
        "Team": "CLE",
        "Position": "QB",
        "Position Rank": 46,
        "ADP": 318.5
    },
    {
        "Rank": 433,
        "Name": "Carson Steele",
        "Team": "KC",
        "Position": "RB",
        "Position Rank": 122,
        "ADP": 331.0
    },
    {
        "Rank": 434,
        "Name": "Mitchell Evans",
        "Team": "CAR",
        "Position": "TE",
        "Position Rank": 57,
        "ADP": 506.0
    },
    {
        "Rank": 435,
        "Name": "Elijah Higgins",
        "Team": "ARI",
        "Position": "TE",
        "Position Rank": 58,
        "ADP": 374.3
    },
    {
        "Rank": 436,
        "Name": "Tyler Johnson",
        "Team": "NYJ",
        "Position": "WR",
        "Position Rank": 153,
        "ADP": 487.5
    },
    {
        "Rank": 437,
        "Name": "New Orleans Saints",
        "Team": "NO",
        "Position": "DST",
        "Position Rank": 28,
        "ADP": 277.3
    },
    {
        "Rank": 438,
        "Name": "Malik Willis",
        "Team": "GB",
        "Position": "QB",
        "Position Rank": 47,
        "ADP": 385.3
    },
    {
        "Rank": 439,
        "Name": "Aidan O'Connell",
        "Team": "LV",
        "Position": "QB",
        "Position Rank": 48,
        "ADP": 429.0
    },
    {
        "Rank": 440,
        "Name": "Javon Baker",
        "Team": "NE",
        "Position": "WR",
        "Position Rank": 154,
        "ADP": 552.0
    },
    {
        "Rank": 441,
        "Name": "Las Vegas Raiders",
        "Team": "LV",
        "Position": "DST",
        "Position Rank": 29,
        "ADP": 268.5
    },
    {
        "Rank": 442,
        "Name": "Mitchell Tinsley",
        "Team": "CIN",
        "Position": "WR",
        "Position Rank": 155,
        "ADP": 334.5
    },
    {
        "Rank": 443,
        "Name": "Michael Carter",
        "Team": "ARI",
        "Position": "RB",
        "Position Rank": 123,
        "ADP": 524.0
    },
    {
        "Rank": 444,
        "Name": "Jake Haener",
        "Team": "NO",
        "Position": "QB",
        "Position Rank": 49,
        "ADP": 695.0
    },
    {
        "Rank": 445,
        "Name": "Sterling Shepard",
        "Team": "TB",
        "Position": "WR",
        "Position Rank": 156,
        "ADP": 385.5
    },
    {
        "Rank": 446,
        "Name": "Carlos Washington Jr.",
        "Team": "ATL",
        "Position": "RB",
        "Position Rank": 124
    },
    {
        "Rank": 447,
        "Name": "Tyquan Thornton",
        "Team": "KC",
        "Position": "WR",
        "Position Rank": 157,
        "ADP": 425.5
    },
    {
        "Rank": 448,
        "Name": "Jake Bobo",
        "Team": "SEA",
        "Position": "WR",
        "Position Rank": 158,
        "ADP": 359.7
    },
    {
        "Rank": 449,
        "Name": "Chris Tyree",
        "Team": "NO",
        "Position": "RB",
        "Position Rank": 125
    },
    {
        "Rank": 450,
        "Name": "Kalif Raymond",
        "Team": "DET",
        "Position": "WR",
        "Position Rank": 159,
        "ADP": 391.0
    },
    {
        "Rank": 451,
        "Name": "Greg Dulcich",
        "Team": "NYG",
        "Position": "TE",
        "Position Rank": 59,
        "ADP": 660.0
    },
    {
        "Rank": 452,
        "Name": "Malachi Corley",
        "Team": "NYJ",
        "Position": "WR",
        "Position Rank": 160,
        "ADP": 743.0
    },
    {
        "Rank": 453,
        "Name": "Hassan Haskins",
        "Team": "LAC",
        "Position": "RB",
        "Position Rank": 126,
        "ADP": 461.0
    },
    {
        "Rank": 454,
        "Name": "Darnell Washington",
        "Team": "PIT",
        "Position": "TE",
        "Position Rank": 60,
        "ADP": 334.0
    },
    {
        "Rank": 455,
        "Name": "Stone Smartt",
        "Team": "NYJ",
        "Position": "TE",
        "Position Rank": 61,
        "ADP": 682.0
    },
    {
        "Rank": 456,
        "Name": "Josh Whyle",
        "Team": "TEN",
        "Position": "TE",
        "Position Rank": 62,
        "ADP": 458.0
    },
    {
        "Rank": 457,
        "Name": "KhaDarel Hodge",
        "Team": "ATL",
        "Position": "WR",
        "Position Rank": 161,
        "ADP": 598.0
    },
    {
        "Rank": 458,
        "Name": "Julian Hill",
        "Team": "MIA",
        "Position": "TE",
        "Position Rank": 63,
        "ADP": 395.0
    },
    {
        "Rank": 459,
        "Name": "Matthew Wright",
        "Team": "FA",
        "Position": "K",
        "Position Rank": 31,
        "ADP": 360.0
    },
    {
        "Rank": 460,
        "Name": "Cordarrelle Patterson",
        "Team": "FA",
        "Position": "RB",
        "Position Rank": 127,
        "ADP": 508.5
    },
    {
        "Rank": 461,
        "Name": "DeeJay Dallas",
        "Team": "ARI",
        "Position": "RB",
        "Position Rank": 128,
        "ADP": 508.0
    },
    {
        "Rank": 462,
        "Name": "Sam Howell",
        "Team": "PHI",
        "Position": "QB",
        "Position Rank": 50,
        "ADP": 488.3
    },
    {
        "Rank": 463,
        "Name": "Luke Farrell",
        "Team": "SF",
        "Position": "TE",
        "Position Rank": 64,
        "ADP": 451.0
    },
    {
        "Rank": 464,
        "Name": "Gardner Minshew II",
        "Team": "KC",
        "Position": "QB",
        "Position Rank": 51,
        "ADP": 394.7
    },
    {
        "Rank": 465,
        "Name": "Zach Wilson",
        "Team": "MIA",
        "Position": "QB",
        "Position Rank": 52,
        "ADP": 478.0
    },
    {
        "Rank": 466,
        "Name": "Jacoby Brissett",
        "Team": "ARI",
        "Position": "QB",
        "Position Rank": 53,
        "ADP": 488.0
    },
    {
        "Rank": 467,
        "Name": "Dylan Laube",
        "Team": "LV",
        "Position": "RB",
        "Position Rank": 129,
        "ADP": 739.0
    },
    {
        "Rank": 468,
        "Name": "Luke Lachey",
        "Team": "HOU",
        "Position": "TE",
        "Position Rank": 65,
        "ADP": 898.0
    },
    {
        "Rank": 469,
        "Name": "Casey Washington",
        "Team": "ATL",
        "Position": "WR",
        "Position Rank": 162,
        "ADP": 730.0
    },
    {
        "Rank": 470,
        "Name": "Jacksonville Jaguars",
        "Team": "JAC",
        "Position": "DST",
        "Position Rank": 30,
        "ADP": 296.0
    },
    {
        "Rank": 471,
        "Name": "K.J. Osborn",
        "Team": "WAS",
        "Position": "WR",
        "Position Rank": 163,
        "ADP": 628.0
    },
    {
        "Rank": 472,
        "Name": "Marcus Yarns",
        "Team": "NO",
        "Position": "RB",
        "Position Rank": 130,
        "ADP": 699.0
    },
    {
        "Rank": 473,
        "Name": "Michael Gallup",
        "Team": "FA",
        "Position": "WR",
        "Position Rank": 164,
        "ADP": 530.0
    },
    {
        "Rank": 474,
        "Name": "Marcus Mariota",
        "Team": "WAS",
        "Position": "QB",
        "Position Rank": 54,
        "ADP": 399.3
    },
    {
        "Rank": 475,
        "Name": "Hunter Long",
        "Team": "JAC",
        "Position": "TE",
        "Position Rank": 66
    },
    {
        "Rank": 476,
        "Name": "Sione Vaki",
        "Team": "DET",
        "Position": "RB",
        "Position Rank": 131,
        "ADP": 487.5
    },
    {
        "Rank": 477,
        "Name": "Tanner Hudson",
        "Team": "CIN",
        "Position": "TE",
        "Position Rank": 67,
        "ADP": 527.0
    },
    {
        "Rank": 478,
        "Name": "Will Howard",
        "Team": "PIT",
        "Position": "QB",
        "Position Rank": 55,
        "ADP": 387.7
    },
    {
        "Rank": 479,
        "Name": "Lucky Jackson",
        "Team": "MIN",
        "Position": "WR",
        "Position Rank": 165,
        "ADP": 443.0
    },
    {
        "Rank": 480,
        "Name": "Tyler Badie",
        "Team": "DEN",
        "Position": "RB",
        "Position Rank": 132,
        "ADP": 459.0
    },
    {
        "Rank": 481,
        "Name": "David Bell",
        "Team": "CLE",
        "Position": "WR",
        "Position Rank": 166,
        "ADP": 644.5
    },
    {
        "Rank": 482,
        "Name": "Hunter Luepke",
        "Team": "DAL",
        "Position": "RB",
        "Position Rank": 133,
        "ADP": 432.0
    },
    {
        "Rank": 483,
        "Name": "Charlie Kolar",
        "Team": "BAL",
        "Position": "TE",
        "Position Rank": 68,
        "ADP": 481.0
    },
    {
        "Rank": 484,
        "Name": "Cooper Rush",
        "Team": "BAL",
        "Position": "QB",
        "Position Rank": 56,
        "ADP": 396.3
    },
    {
        "Rank": 485,
        "Name": "Daniel Bellinger",
        "Team": "NYG",
        "Position": "TE",
        "Position Rank": 69,
        "ADP": 405.5
    },
    {
        "Rank": 486,
        "Name": "Tennessee Titans",
        "Team": "TEN",
        "Position": "DST",
        "Position Rank": 31,
        "ADP": 295.3
    },
    {
        "Rank": 487,
        "Name": "Deuce Vaughn",
        "Team": "DAL",
        "Position": "RB",
        "Position Rank": 134,
        "ADP": 389.7
    },
    {
        "Rank": 488,
        "Name": "Carolina Panthers",
        "Team": "CAR",
        "Position": "DST",
        "Position Rank": 32,
        "ADP": 302.7
    },
    {
        "Rank": 489,
        "Name": "Tyson Bagent",
        "Team": "CHI",
        "Position": "QB",
        "Position Rank": 57,
        "ADP": 496.0
    },
    {
        "Rank": 490,
        "Name": "Mac Jones",
        "Team": "SF",
        "Position": "QB",
        "Position Rank": 58,
        "ADP": 388.7
    },
    {
        "Rank": 491,
        "Name": "C.J. Ham",
        "Team": "MIN",
        "Position": "RB",
        "Position Rank": 135,
        "ADP": 370.0
    },
    {
        "Rank": 492,
        "Name": "Ronnie Rivers",
        "Team": "LAR",
        "Position": "RB",
        "Position Rank": 136,
        "ADP": 681.0
    },
    {
        "Rank": 493,
        "Name": "Trent Sherfield Sr.",
        "Team": "DEN",
        "Position": "WR",
        "Position Rank": 167,
        "ADP": 804.0
    },
    {
        "Rank": 494,
        "Name": "Patrick Ricard",
        "Team": "BAL",
        "Position": "RB",
        "Position Rank": 137,
        "ADP": 406.0
    },
    {
        "Rank": 495,
        "Name": "Colby Parkinson",
        "Team": "LAR",
        "Position": "TE",
        "Position Rank": 70,
        "ADP": 443.0
    },
    {
        "Rank": 496,
        "Name": "Kylen Granson",
        "Team": "PHI",
        "Position": "TE",
        "Position Rank": 71,
        "ADP": 455.0
    },
    {
        "Rank": 497,
        "Name": "Thomas Fidone II",
        "Team": "NYG",
        "Position": "TE",
        "Position Rank": 72,
        "ADP": 545.0
    },
    {
        "Rank": 498,
        "Name": "Drew Lock",
        "Team": "SEA",
        "Position": "QB",
        "Position Rank": 59,
        "ADP": 393.5
    },
    {
        "Rank": 499,
        "Name": "Michael Burton",
        "Team": "DEN",
        "Position": "RB",
        "Position Rank": 138,
        "ADP": 468.0
    },
    {
        "Rank": 500,
        "Name": "Jeff Wilson Jr.",
        "Team": "SF",
        "Position": "RB",
        "Position Rank": 139,
        "ADP": 495.5
    },
    {
        "Rank": 501,
        "Name": "Andrew Beck",
        "Team": "NYJ",
        "Position": "TE",
        "Position Rank": 73,
        "ADP": 655.0
    },
    {
        "Rank": 502,
        "Name": "Bub Means",
        "Team": "NO",
        "Position": "WR",
        "Position Rank": 168,
        "ADP": 741.0
    },
    {
        "Rank": 503,
        "Name": "Jase McClellan",
        "Team": "FA",
        "Position": "RB",
        "Position Rank": 140
    },
    {
        "Rank": 504,
        "Name": "Ezekiel Elliott",
        "Team": "FA",
        "Position": "RB",
        "Position Rank": 141,
        "ADP": 288.0
    },
    {
        "Rank": 505,
        "Name": "Harrison Bryant",
        "Team": "HOU",
        "Position": "TE",
        "Position Rank": 74,
        "ADP": 507.0
    },
    {
        "Rank": 506,
        "Name": "Brock Wright",
        "Team": "DET",
        "Position": "TE",
        "Position Rank": 75,
        "ADP": 311.5
    },
    {
        "Rank": 507,
        "Name": "David Moore",
        "Team": "CAR",
        "Position": "WR",
        "Position Rank": 169,
        "ADP": 387.0
    },
    {
        "Rank": 508,
        "Name": "John Bates",
        "Team": "WAS",
        "Position": "TE",
        "Position Rank": 76,
        "ADP": 477.0
    },
    {
        "Rank": 509,
        "Name": "Charlie Woerner",
        "Team": "ATL",
        "Position": "TE",
        "Position Rank": 77,
        "ADP": 634.0
    },
    {
        "Rank": 510,
        "Name": "Cedrick Wilson Jr.",
        "Team": "NO",
        "Position": "WR",
        "Position Rank": 170,
        "ADP": 492.5
    },
    {
        "Rank": 511,
        "Name": "Jake Browning",
        "Team": "CIN",
        "Position": "QB",
        "Position Rank": 60,
        "ADP": 411.3
    },
    {
        "Rank": 512,
        "Name": "Nick Nash",
        "Team": "ATL",
        "Position": "WR",
        "Position Rank": 171,
        "ADP": 666.5
    },
    {
        "Rank": 513,
        "Name": "Rasheen Ali",
        "Team": "BAL",
        "Position": "RB",
        "Position Rank": 142,
        "ADP": 440.0
    },
    {
        "Rank": 514,
        "Name": "Kyle Trask",
        "Team": "FA",
        "Position": "QB",
        "Position Rank": 61,
        "ADP": 540.5
    },
    {
        "Rank": 515,
        "Name": "Adam Trautman",
        "Team": "DEN",
        "Position": "TE",
        "Position Rank": 78,
        "ADP": 350.0
    },
    {
        "Rank": 516,
        "Name": "Derius Davis",
        "Team": "LAC",
        "Position": "WR",
        "Position Rank": 172,
        "ADP": 463.0
    },
    {
        "Rank": 517,
        "Name": "Tylan Wallace",
        "Team": "BAL",
        "Position": "WR",
        "Position Rank": 173,
        "ADP": 387.0
    },
    {
        "Rank": 518,
        "Name": "Scotty Miller",
        "Team": "PIT",
        "Position": "WR",
        "Position Rank": 174,
        "ADP": 460.5
    },
    {
        "Rank": 519,
        "Name": "Brycen Tremayne",
        "Team": "CAR",
        "Position": "WR",
        "Position Rank": 175
    },
    {
        "Rank": 520,
        "Name": "Chris Blair",
        "Team": "ATL",
        "Position": "WR",
        "Position Rank": 176
    },
    {
        "Rank": 521,
        "Name": "Jelani Woods",
        "Team": "IND",
        "Position": "TE",
        "Position Rank": 79,
        "ADP": 662.0
    },
    {
        "Rank": 522,
        "Name": "Johnny Mundt",
        "Team": "JAC",
        "Position": "TE",
        "Position Rank": 80,
        "ADP": 582.0
    },
    {
        "Rank": 523,
        "Name": "Lucas Krull",
        "Team": "DEN",
        "Position": "TE",
        "Position Rank": 81,
        "ADP": 679.0
    }
]